notifyexceptions/__init__.py
notifyexceptions/notifyexceptions.py
notifyexceptions-1.1.dist-info/METADATA
notifyexceptions-1.1.dist-info/RECORD
notifyexceptions-1.1.dist-info/WHEEL
notifyexceptions-1.1.dist-info/top_level.txt
