Metadata-Version: 2.1
Name: notifyexceptions
Version: 1.1
Summary: Get exception on ADMINS mail IDs
Home-page: http://pypi.python.org/pypi/notifyexceptions
Author: Shashank Shukla
Author-email: shuklashashank@outlook.com
License: UNKNOWN
Platform: UNKNOWN
Requires-Dist: Django (>=1.8)
